redis_func_cache/__init__.py
redis_func_cache/_version.py
redis_func_cache/cache.py
redis_func_cache/constants.py
redis_func_cache/exceptions.py
redis_func_cache/py.typed
redis_func_cache/typing.py
redis_func_cache/utils.py
redis_func_cache/lua/fifo_get.lua
redis_func_cache/lua/fifo_put.lua
redis_func_cache/lua/fifo_t_put.lua
redis_func_cache/lua/lfu_get.lua
redis_func_cache/lua/lfu_put.lua
redis_func_cache/lua/lru_get.lua
redis_func_cache/lua/lru_put.lua
redis_func_cache/lua/lru_t_get.lua
redis_func_cache/lua/lru_t_put.lua
redis_func_cache/lua/rr_get.lua
redis_func_cache/lua/rr_put.lua
redis_func_cache/mixins/__init__.py
redis_func_cache/mixins/hash.py
redis_func_cache/mixins/scripts.py
redis_func_cache/policies/__init__.py
redis_func_cache/policies/abstract.py
redis_func_cache/policies/base.py
redis_func_cache/policies/fifo.py
redis_func_cache/policies/lfu.py
redis_func_cache/policies/lru.py
redis_func_cache/policies/mru.py
redis_func_cache/policies/rr.py
redis_func_cache-0.6.0.dist-info/licenses/LICENSE.md
redis_func_cache-0.6.0.dist-info/METADATA
redis_func_cache-0.6.0.dist-info/WHEEL
redis_func_cache-0.6.0.dist-info/top_level.txt
redis_func_cache-0.6.0.dist-info/RECORD
