Metadata-Version: 2.4
Name: redis_func_cache
Version: 0.6.0
Summary: A Python library that provides decorators for caching function results in Redis, supporting multiple serialization formats and caching strategies, as well as asynchronous operations.
Author-email: Liu Xue-Yan <liu_xue_yan@foxmail.com>
License-Expression: BSD-3-Clause
Project-URL: homepage, https://github.com/tanbro/redis_func_cache
Project-URL: changelog, https://github.com/tanbro/redis_func_cache/main/CHANGELOG.md
Project-URL: documentation, https://redis-func-cache.readthedocs.io/
Project-URL: issues, https://github.com/tanbro/redis_func_cache/issues
Project-URL: source, https://github.com/tanbro/redis_func_cache.git
Keywords: redis,cache,decorator
Classifier: Development Status :: 5 - Production/Stable
Classifier: Intended Audience :: Developers
Classifier: Programming Language :: Lua
Classifier: Programming Language :: Python
Classifier: Topic :: Software Development :: Libraries :: Python Modules
Classifier: Typing :: Typed
Requires-Python: >=3.9
License-File: LICENSE.md
Requires-Dist: redis>=3.5.0
Requires-Dist: importlib-resources>=5.12; python_version < "3.9"
Requires-Dist: typing-extensions>=4.5.0; python_version < "3.12"
Provides-Extra: hiredis
Requires-Dist: redis[hiredis]; extra == "hiredis"
Provides-Extra: pygments
Requires-Dist: Pygments>=2.9; extra == "pygments"
Provides-Extra: bson
Requires-Dist: pymongo>=3.9; extra == "bson"
Provides-Extra: msgpack
Requires-Dist: msgpack>=1.0; extra == "msgpack"
Provides-Extra: yaml
Requires-Dist: PyYAML>=5.4; extra == "yaml"
Provides-Extra: cbor
Requires-Dist: cbor2>=5.0; extra == "cbor"
Provides-Extra: cloudpickle
Requires-Dist: cloudpickle>=3.0; extra == "cloudpickle"
Provides-Extra: all
Requires-Dist: redis[hiredis]; extra == "all"
Requires-Dist: Pygments>=2.9; extra == "all"
Requires-Dist: pymongo>=3.9; extra == "all"
Requires-Dist: msgpack>=1.0; extra == "all"
Requires-Dist: PyYAML>=5.4; extra == "all"
Requires-Dist: cloudpickle>=3.0; extra == "all"
Dynamic: license-file
